PyQt6/Qt6/translations/qscintilla_cs.qm
PyQt6/Qt6/translations/qscintilla_de.qm
PyQt6/Qt6/translations/qscintilla_es.qm
PyQt6/Qt6/translations/qscintilla_fr.qm
PyQt6/Qt6/translations/qscintilla_pt_br.qm
PyQt6/Qsci.pyd
PyQt6/Qsci.pyi
PyQt6/Qt6/qsci/api/python/PyQt6-QScintilla.api
PyQt6/Qt6/qsci/api/python/Python-2.4.api
PyQt6/Qt6/qsci/api/python/Python-2.5.api
PyQt6/Qt6/qsci/api/python/Python-2.6.api
PyQt6/Qt6/qsci/api/python/Python-2.7.api
PyQt6/Qt6/qsci/api/python/Python-3.1.api
PyQt6/Qt6/qsci/api/python/Python-3.10.api
PyQt6/Qt6/qsci/api/python/Python-3.11.api
PyQt6/Qt6/qsci/api/python/Python-3.2.api
PyQt6/Qt6/qsci/api/python/Python-3.3.api
PyQt6/Qt6/qsci/api/python/Python-3.4.api
PyQt6/Qt6/qsci/api/python/Python-3.5.api
PyQt6/Qt6/qsci/api/python/Python-3.6.api
PyQt6/Qt6/qsci/api/python/Python-3.7.api
PyQt6/Qt6/qsci/api/python/Python-3.8.api
PyQt6/Qt6/qsci/api/python/Python-3.9.api
PyQt6/bindings/Qsci/Qsci.toml
PyQt6/bindings/Qsci/qsciabstractapis.sip
PyQt6/bindings/Qsci/qsciapis.sip
PyQt6/bindings/Qsci/qscicommand.sip
PyQt6/bindings/Qsci/qscicommandset.sip
PyQt6/bindings/Qsci/qscidocument.sip
PyQt6/bindings/Qsci/qscilexer.sip
PyQt6/bindings/Qsci/qscilexerasm.sip
PyQt6/bindings/Qsci/qscilexeravs.sip
PyQt6/bindings/Qsci/qscilexerbash.sip
PyQt6/bindings/Qsci/qscilexerbatch.sip
PyQt6/bindings/Qsci/qscilexercmake.sip
PyQt6/bindings/Qsci/qscilexercoffeescript.sip
PyQt6/bindings/Qsci/qscilexercpp.sip
PyQt6/bindings/Qsci/qscilexercsharp.sip
PyQt6/bindings/Qsci/qscilexercss.sip
PyQt6/bindings/Qsci/qscilexercustom.sip
PyQt6/bindings/Qsci/qscilexerd.sip
PyQt6/bindings/Qsci/qscilexerdiff.sip
PyQt6/bindings/Qsci/qscilexerfortran.sip
PyQt6/bindings/Qsci/qscilexerfortran77.sip
PyQt6/bindings/Qsci/qscilexerhex.sip
PyQt6/bindings/Qsci/qscilexerhtml.sip
PyQt6/bindings/Qsci/qscilexeridl.sip
PyQt6/bindings/Qsci/qscilexerintelhex.sip
PyQt6/bindings/Qsci/qscilexerjava.sip
PyQt6/bindings/Qsci/qscilexerjavascript.sip
PyQt6_QScintilla-2.14.1.dist-info/WHEEL
PyQt6_QScintilla-2.14.1.dist-info/METADATA
PyQt6_QScintilla-2.14.1.dist-info/RECORD
