Metadata-Version: 2.1
Name: PyQt6-QScintilla
Version: 2.14.1
Requires-Python: >=3.9
Summary: Python bindings for the QScintilla programmers editor widget
Project-Url: homepage, https://www.riverbankcomputing.com/software/qscintilla/
Requires-Dist: PyQt6-sip (>=13.6, <14)
Requires-Dist: PyQt6 (>=6.0.3)
License: GPL v3
Author-Email: Riverbank Computing Limited <info@riverbankcomputing.com>
